pdh/__init__.py
pdh/config.py
pdh/core.py
pdh/filters.py
pdh/main.py
pdh/output.py
pdh/pd.py
pdh/rules.py
pdh/transformations.py
pdh-0.8.0.dist-info/LICENSE
pdh-0.8.0.dist-info/METADATA
pdh-0.8.0.dist-info/WHEEL
pdh-0.8.0.dist-info/entry_points.txt
pdh-0.8.0.dist-info/RECORD
