Metadata-Version: 2.1
Name: pdh
Version: 0.8.0
Summary: Pagerduty CLI for Humans
Home-page: https://github.com/mbovo/pdh
License: GPL-3.0-or-later
Author: Manuel Bovo
Author-email: manuel.bovo@gmail.com
Requires-Python: >=3.11,<4.0
Classifier: License :: OSI Approved :: GNU General Public License v3 or later (GPLv3+)
Classifier: Programming Language :: Python :: 3
Classifier: Programming Language :: Python :: 3.11
Classifier: Programming Language :: Python :: 3.12
Classifier: Programming Language :: Python :: 3.13
Requires-Dist: PyYAML (>=6.0.2,<7.0.0)
Requires-Dist: click (>=8.1.7,<9.0.0)
Requires-Dist: colorama (>=0.4.6,<0.5.0)
Requires-Dist: deprecation (>=2.1.0,<3.0.0)
Requires-Dist: dikdik (>=0.1.6,<0.2.0)
Requires-Dist: humanize (>=4.10.0,<5.0.0)
Requires-Dist: jsonpath-ng (>=1.7.0,<2.0.0)
Requires-Dist: pdpyras (>=5.4.0,<6.0.0)
Requires-Dist: rich (>=13.9.4,<14.0.0)
Requires-Dist: setuptools (>=72.1.0,<73.0.0)
Project-URL: Repository, https://github.com/mbovo/pdh
